evsrc/__init__.py
evsrc/bootstrap.py
evsrc/infra/__init__.py
evsrc/infra/inmem.py
evsrc/infra/json.py
evsrc/infra/pickle.py
evsrc/lib/__init__.py
evsrc/lib/model.py
evsrc/lib/ports.py
evsrc/lib/repos.py
evsrc/lib/stores.py
evsrc-4.0.7.dist-info/METADATA
evsrc-4.0.7.dist-info/WHEEL
evsrc-4.0.7.dist-info/RECORD
