Metadata-Version: 2.4
Name: evsrc
Version: 4.0.7
Summary: Event Sourcing library using python
Author-email: Salvador Ruiz <salvador.ruiz.r@gmail.com>
License: LGPL-3.0-or-later
Requires-Python: >=3.13
Requires-Dist: dcjdict>=0.2.0
